rainbowneko/__init__.py
rainbowneko/_share.py
rainbowneko/cfgs/launcher/deepspeed.yaml
rainbowneko/cfgs/launcher/multi.yaml
rainbowneko/cfgs/launcher/single.yaml
rainbowneko/cfgs/py/eval/multi_class.py
rainbowneko/cfgs/py/eval/multi_class_flow.py
rainbowneko/cfgs/py/infer/multi_class.py
rainbowneko/cfgs/py/train/train_base.py
rainbowneko/cfgs/py/train/tuning_base.py
rainbowneko/cfgs/py/train/classify/distillation.py
rainbowneko/cfgs/py/train/classify/multi_class.py
rainbowneko/cfgs/py/train/classify/multi_class_dynamic_wd.py
rainbowneko/cfgs/py/train/classify/multi_class_floweval.py
rainbowneko/cfgs/py/train/classify/multi_class_mixup.py
rainbowneko/cfgs/py/train/classify/multi_class_onnx.py
rainbowneko/cfgs/py/train/classify/multi_class_webds.py
rainbowneko/cfgs/py/train/classify/semi_supervise.py
rainbowneko/cfgs/yaml/train/train_base.yaml
rainbowneko/cfgs/yaml/train/tuning_base.yaml
rainbowneko/cfgs/yaml/train/classify/multi_class.yaml
rainbowneko/ckpt_manager/__init__.py
rainbowneko/ckpt_manager/base.py
rainbowneko/ckpt_manager/ckpt.py
rainbowneko/ckpt_manager/locator.py
rainbowneko/ckpt_manager/model.py
rainbowneko/ckpt_manager/resume.py
rainbowneko/ckpt_manager/deepspeed/__init__.py
rainbowneko/ckpt_manager/deepspeed/optim.py
rainbowneko/ckpt_manager/format/__init__.py
rainbowneko/ckpt_manager/format/base.py
rainbowneko/ckpt_manager/format/onnx.py
rainbowneko/ckpt_manager/format/pkl.py
rainbowneko/ckpt_manager/format/safetensor.py
rainbowneko/ckpt_manager/source/__init__.py
rainbowneko/ckpt_manager/source/base.py
rainbowneko/ckpt_manager/source/local.py
rainbowneko/data/__init__.py
rainbowneko/data/cache.py
rainbowneko/data/data_loader.py
rainbowneko/data/dataset.py
rainbowneko/data/label_loader.py
rainbowneko/data/sampler.py
rainbowneko/data/utils.py
rainbowneko/data/webds.py
rainbowneko/data/bucket/__init__.py
rainbowneko/data/bucket/base.py
rainbowneko/data/bucket/contrastive.py
rainbowneko/data/bucket/fixed.py
rainbowneko/data/bucket/long_edge.py
rainbowneko-1.10.0.dist-info/licenses/LICENSE
rainbowneko-1.10.0.dist-info/METADATA
rainbowneko-1.10.0.dist-info/WHEEL
rainbowneko-1.10.0.dist-info/entry_points.txt
rainbowneko-1.10.0.dist-info/top_level.txt
rainbowneko-1.10.0.dist-info/RECORD
