Metadata-Version: 2.4
Name: rainbowneko
Version: 1.10.0
Summary: Neural network training and inference framework
Home-page: https://github.com/IrisRainbowNeko/RainbowNekoEngine
Author: IrisRainbowNeko
Author-email: rainbow-neko@outlook.com
Classifier: License :: OSI Approved :: Apache Software License
Classifier: Operating System :: OS Independent
Classifier: Programming Language :: Python :: 3
Classifier: Programming Language :: Python :: 3.8
Classifier: Programming Language :: Python :: 3.9
Classifier: Programming Language :: Python :: 3.10
Classifier: Programming Language :: Python :: 3.11
Classifier: Programming Language :: Python :: 3.12
Classifier: Topic :: Scientific/Engineering :: Artificial Intelligence
Requires-Python: >=3.8
License-File: LICENSE
Requires-Dist: accelerate>=0.15.0
Requires-Dist: torchmetrics
Requires-Dist: safetensors
Requires-Dist: einops>=0.6.0
Requires-Dist: hydra-core
Requires-Dist: loguru
Requires-Dist: numpy
Requires-Dist: omegaconf
Requires-Dist: opencv_python
Requires-Dist: Pillow
Requires-Dist: PyYAML
Requires-Dist: scikit_learn
Requires-Dist: tqdm
Requires-Dist: addict
Requires-Dist: albumentations
Requires-Dist: rich
Requires-Dist: yapf
Requires-Dist: pandas
Requires-Dist: pyzmq
Requires-Dist: bitsandbytes
Dynamic: author
Dynamic: author-email
Dynamic: classifier
Dynamic: description
Dynamic: description-content-type
Dynamic: home-page
Dynamic: license-file
Dynamic: requires-dist
Dynamic: requires-python
Dynamic: summary
